listen_ytx/__init__.py
listen_ytx/listen.py
listen_ytx-0.1.7.dist-info/licenses/LICENSE
listen_ytx-0.1.7.dist-info/METADATA
listen_ytx-0.1.7.dist-info/WHEEL
listen_ytx-0.1.7.dist-info/entry_points.txt
listen_ytx-0.1.7.dist-info/top_level.txt
listen_ytx-0.1.7.dist-info/RECORD
